ensight2obj.py
ensight2vtk.py
ensight_transform.py
ensightreader.py
ensight_reader-0.13.1.dist-info/licenses/LICENSE.txt
ensight_reader-0.13.1.dist-info/METADATA
ensight_reader-0.13.1.dist-info/WHEEL
ensight_reader-0.13.1.dist-info/entry_points.txt
ensight_reader-0.13.1.dist-info/top_level.txt
ensight_reader-0.13.1.dist-info/RECORD
