Metadata-Version: 2.4
Name: ensight-reader
Version: 0.13.1
Summary: A pure Python reader for the EnSight Gold format
Home-page: https://github.com/tkarabela/ensight-reader
Author: Tomas Karabela
Author-email: tkarabela@seznam.cz
License: MIT
Project-URL: Documentation, https://ensight-reader.readthedocs.io
Project-URL: Bug Tracker, https://github.com/tkarabela/ensight-reader/issues
Classifier: Development Status :: 4 - Beta
Classifier: Intended Audience :: Developers
Classifier: Intended Audience :: Science/Research
Classifier: License :: OSI Approved :: MIT License
Classifier: Operating System :: OS Independent
Classifier: Programming Language :: Python :: 3
Classifier: Programming Language :: Python :: 3.9
Classifier: Programming Language :: Python :: 3.10
Classifier: Programming Language :: Python :: 3.11
Classifier: Programming Language :: Python :: 3.12
Classifier: Programming Language :: Python :: 3.13
Classifier: Programming Language :: Python :: 3.14
Classifier: Topic :: Scientific/Engineering
Classifier: Typing :: Typed
Requires-Python: >=3.9
License-File: LICENSE.txt
Requires-Dist: numpy>=1.22
Dynamic: license-file
